[
  {
            "automation_name": "tone",
            "trigger": "Schedule",
            "applications": ["gmail.png","slack.png"],
            "created_by": {
            "name": "Divyansh",
            "time": "07/05/2024 17:25"
            },
            "last_modified_by": {
            "name": "New user",
            "time": "07/05/2024 17:25"
            }
            
        },
        {
            "automation_name": "yoworking",
            "trigger": "Schedule",
            "applications": ["gmail.png"],
            "created_by": {
            "name": "Random",
            "time": "07/05/2024 17:25"
            },
            "last_modified_by": {
            "name": "Previous user",
            "time": "07/05/2024 17:25"
            }
        },
        {
            "automation_name": "yesactually",
            "trigger": "Schedule",
            "applications": ["gmail.png","slack.png"],
            "created_by": {
            "name": "Shivam",
            "time": "07/05/2024 17:25"
            },
            "last_modified_by": {
            "name": "Divyansh",
            "time": "07/05/2024 17:25"
            }
        },
        {
            "automation_name": "Untitled",
            "trigger": "Callable",
            "applications": ["slack.png"],
           "created_by": {
            "name": "Abhishek",
            "time": "07/05/2024 17:25"
            },
            "last_modified_by": {
            "name": "Superadmin",
            "time": "07/05/2024 17:25"
            }
        },
        {
            "automation_name": "rohan",
            "trigger": "Application",
            "applications": ["gmail.png"],
            "created_by": {
            "name": "Harshal",
            "time": "07/05/2024 17:25"
            },
            "last_modified_by": {
            "name": "Unknown",
            "time": "07/05/2024 17:25"
            }
        },
        {
            "automation_name": "xyz",
            "trigger": "Application",
            "applications": ["gmail.png","slack.png"],
            "created_by": {
            "name": "Orz",
            "time": "07/05/2024 17:25"
            },
            "last_modified_by": {
            "name": "Ritik",
            "time": "07/05/2024 17:25"
            }
        },
        {
            "automation_name": "gfh",
            "trigger": "Schedule",
            "applications": ["gmail.png","slack.png"],
            "created_by": {
            "name": "Guess",
            "time": "07/05/2024 17:25"
            },
            "last_modified_by": {
            "name": "Root",
            "time": "07/05/2024 17:25"
            }
        },
        {
            "automation_name": "send invite",
            "trigger": "Callable",
            "applications": ["gmail.png","slack.png"],
            "project": "SS",
            "created_by": {
            "name": "Krypto",
            "time": "07/05/2024 17:25"
            },
            "last_modified_by": {
            "name": "Kane",
            "time": "07/05/2024 17:25"
            }
        },
        {
            "automation_name": "hgjkl",
            "trigger": "Schedule",
            "applications": ["gmail.png","slack.png"],
            "created_by": {
            "name": "Unifyapps Admin",
            "time": "07/05/2024 17:25"
            },
            "last_modified_by": {
            "name": "Smith",
            "time": "07/05/2024 17:25"
            }
        },
        {
            "automation_name": "vbnm",
            "trigger": "Schedule",
            "applications": ["gmail.png","slack.png"],
            "created_by": {
            "name": "Unifyapps Admin",
            "time": "07/05/2024 17:25"
            },
            "last_modified_by": {
            "name": "VK",
            "time": "07/05/2024 17:25"
            }
        },
        {
            "automation_name": "SavePhoneNumber",
            "trigger": "Callable",
            "applications": ["gmail.png","slack.png"],
            "created_by": {
            "name": "Unifyapps Admin",
            "time": "07/05/2024 17:25"
            },
            "last_modified_by": {
            "name": "Unifyapps Admin",
            "time": "07/05/2024 17:25"
            }
        },
        {
            "automation_name": "Untitled",
            "trigger": "Application",
            "applications": ["gmail.png","slack.png"],
            "created_by": {
            "name": "Unifyapps Admin",
            "time": "07/05/2024 17:25"
            },
            "last_modified_by": {
            "name": "Unifyapps Admin",
            "time": "07/05/2024 17:25"
            }
        },
        {
            "automation_name": "gvfhbjkn",
            "trigger": "Schedule",
            "applications": ["gmail.png","slack.png"],
            "created_by": {
            "name": "Unifyapps Admin",
            "time": "07/05/2024 17:25"
            },
            "last_modified_by": {
            "name": "Unifyapps Admin",
            "time": "07/05/2024 17:25"
            }
        }
        
]